backports/__init__.py
backports/zoneinfo/__init__.py
docassemble_backports-1.0.dist-info/LICENSE.txt
docassemble_backports-1.0.dist-info/METADATA
docassemble_backports-1.0.dist-info/WHEEL
docassemble_backports-1.0.dist-info/top_level.txt
docassemble_backports-1.0.dist-info/RECORD
